LICENSE
MANIFEST.in
README.rst
setup.py
tox.ini
Mopidy_Banshee.egg-info/PKG-INFO
Mopidy_Banshee.egg-info/SOURCES.txt
Mopidy_Banshee.egg-info/dependency_links.txt
Mopidy_Banshee.egg-info/entry_points.txt
Mopidy_Banshee.egg-info/not-zip-safe
Mopidy_Banshee.egg-info/requires.txt
Mopidy_Banshee.egg-info/top_level.txt
mopidy_banshee/__init__.py
mopidy_banshee/banshee.py
mopidy_banshee/ext.conf