Metadata-Version: 1.1
Name: Mopidy-Banshee
Version: 0.1.2
Summary: Banshee extension for Mopidy
Home-page: http://github.com/tamland/mopidy-banshee
Author: Thomas Amland
Author-email: thomas.amland@googlemail.com
License: Apache License, Version 2.0
Keywords: m,o,p,i,d,y, ,b,a,n,s,h,e,e
Platform: UNKNOWN
Classifier: Development Status :: 3 - Alpha
Classifier: Intended Audience :: End Users/Desktop
Classifier: Environment :: No Input/Output (Daemon)
Classifier: Topic :: Multimedia :: Sound/Audio :: Players
Classifier: License :: OSI Approved :: Apache Software License
Classifier: Programming Language :: Python :: 2
Classifier: Programming Language :: Python :: 2.6
Classifier: Programming Language :: Python :: 2.7
Classifier: Programming Language :: Python :: 3
Classifier: Programming Language :: Python :: 3.3
Classifier: Programming Language :: Python :: 3.4
